better_notion/__init__.py
better_notion/_api/__init__.py
better_notion/_api/client.py
better_notion/_api/errors.py
better_notion/_api/oauth.py
better_notion/_api/collections/__init__.py
better_notion/_api/collections/blocks.py
better_notion/_api/collections/comments.py
better_notion/_api/collections/databases.py
better_notion/_api/collections/pages.py
better_notion/_api/collections/users.py
better_notion/_api/entities/__init__.py
better_notion/_api/entities/block.py
better_notion/_api/entities/comment.py
better_notion/_api/entities/database.py
better_notion/_api/entities/page.py
better_notion/_api/entities/user.py
better_notion/_api/properties/__init__.py
better_notion/_api/properties/base.py
better_notion/_api/properties/checkbox.py
better_notion/_api/properties/date.py
better_notion/_api/properties/email.py
better_notion/_api/properties/number.py
better_notion/_api/properties/phone.py
better_notion/_api/properties/relation.py
better_notion/_api/properties/rich_text.py
better_notion/_api/properties/select.py
better_notion/_api/properties/title.py
better_notion/_api/properties/url.py
better_notion/_api/utils/__init__.py
better_notion/_api/utils/pagination.py
better_notion/_cli/__init__.py
better_notion/_cli/async_typer.py
better_notion/_cli/config.py
better_notion/_cli/display.py
better_notion/_cli/errors.py
better_notion/_cli/main.py
better_notion/_cli/markdown.py
better_notion/_cli/response.py
better_notion/_cli/commands/__init__.py
better_notion/_cli/commands/auth.py
better_notion/_cli/commands/blocks.py
better_notion/_cli/commands/comments.py
better_notion/_cli/commands/config.py
better_notion/_cli/commands/databases.py
better_notion/_cli/commands/pages.py
better_notion/_cli/commands/plugins.py
better_notion/_cli/commands/search.py
better_notion/_cli/commands/update.py
better_notion/_cli/commands/users.py
better_notion/_cli/commands/workspace.py
better_notion/_cli/docs/__init__.py
better_notion/_cli/docs/base.py
better_notion/_cli/docs/formatters.py
better_notion-1.9.1.dist-info/METADATA
better_notion-1.9.1.dist-info/WHEEL
better_notion-1.9.1.dist-info/entry_points.txt
better_notion-1.9.1.dist-info/licenses/LICENSE
better_notion-1.9.1.dist-info/RECORD
