Metadata-Version: 2.4
Name: better-notion
Version: 1.9.1
Summary: A high-level Python SDK for the Notion API with developer experience in mind.
Project-URL: Homepage, https://github.com/nesalia-inc/better-notion
Project-URL: Documentation, https://github.com/nesalia-inc/better-notion#readme
Project-URL: Repository, https://github.com/nesalia-inc/better-notion
Project-URL: Issues, https://github.com/nesalia-inc/better-notion/issues
Author-email: Nesalia Inc <contact@nesalia.com>
License: MIT
License-File: LICENSE
Keywords: api,notion,notion-api,productivity,sdk
Classifier: Development Status :: 4 - Beta
Classifier: Intended Audience :: Developers
Classifier: License :: OSI Approved :: MIT License
Classifier: Programming Language :: Python :: 3
Classifier: Programming Language :: Python :: 3.10
Classifier: Programming Language :: Python :: 3.11
Classifier: Programming Language :: Python :: 3.12
Classifier: Programming Language :: Python :: 3.13
Classifier: Programming Language :: Python :: 3.14
Classifier: Topic :: Office/Business
Classifier: Topic :: Software Development :: Libraries :: Python Modules
Classifier: Typing :: Typed
Requires-Python: >=3.10
Requires-Dist: httpx<0.28.0,>=0.27.0
Requires-Dist: pydantic<3.0.0,>=2.0.0
Requires-Dist: rich<14.0.0,>=13.0.0
Requires-Dist: typing-extensions>=4.0.0
Provides-Extra: all
Requires-Dist: asyncer>=0.0.5; extra == 'all'
Requires-Dist: click<8.2.0,>=8.1.0; extra == 'all'
Requires-Dist: mypy>=1.0.0; extra == 'all'
Requires-Dist: pre-commit>=3.0.0; extra == 'all'
Requires-Dist: pytest-asyncio>=0.21.0; extra == 'all'
Requires-Dist: pytest-cov>=4.0.0; extra == 'all'
Requires-Dist: pytest-mock>=3.10.0; extra == 'all'
Requires-Dist: pytest>=7.0.0; extra == 'all'
Requires-Dist: python-dotenv>=1.0.0; extra == 'all'
Requires-Dist: rich<14.0.0,>=13.0.0; extra == 'all'
Requires-Dist: ruff>=0.1.0; extra == 'all'
Requires-Dist: typer<0.13.0,>=0.12.0; extra == 'all'
Provides-Extra: cli
Requires-Dist: asyncer>=0.0.5; extra == 'cli'
Requires-Dist: click<8.2.0,>=8.1.0; extra == 'cli'
Requires-Dist: rich<14.0.0,>=13.0.0; extra == 'cli'
Requires-Dist: typer<0.13.0,>=0.12.0; extra == 'cli'
Provides-Extra: dev
Requires-Dist: mypy>=1.0.0; extra == 'dev'
Requires-Dist: pre-commit>=3.0.0; extra == 'dev'
Requires-Dist: pytest-asyncio>=0.21.0; extra == 'dev'
Requires-Dist: pytest-cov>=4.0.0; extra == 'dev'
Requires-Dist: pytest-mock>=3.10.0; extra == 'dev'
Requires-Dist: pytest>=7.0.0; extra == 'dev'
Requires-Dist: python-dotenv>=1.0.0; extra == 'dev'
Requires-Dist: ruff>=0.1.0; extra == 'dev'
